tapdance/__init__.py
tapdance/cli.py
tapdance/config.py
tapdance/docker.py
tapdance/install_helper.py
tapdance/plans.py
tapdance/states.py
tapdance/syncs.py
tapdance-0.9.9.dist-info/entry_points.txt
tapdance-0.9.9.dist-info/LICENSE
tapdance-0.9.9.dist-info/WHEEL
tapdance-0.9.9.dist-info/METADATA
tapdance-0.9.9.dist-info/RECORD
