Metadata-Version: 2.1
Name: tapdance
Version: 0.9.9
Summary: Tapdance is an orchestration layer for the open source Singer tap platform.
License: MIT
Author: AJ Steers
Author-email: aj.steers@slalom.com
Requires-Python: >=3.7,<4.0
Classifier: License :: OSI Approved :: MIT License
Classifier: Programming Language :: Python :: 3
Classifier: Programming Language :: Python :: 3.10
Classifier: Programming Language :: Python :: 3.7
Classifier: Programming Language :: Python :: 3.8
Classifier: Programming Language :: Python :: 3.9
Provides-Extra: aws
Provides-Extra: azure
Requires-Dist: PyYAML (>=5.4.1,<6.0.0)
Requires-Dist: azure-storage-blob (>=12.7.1,<13.0.0); extra == "azure"
Requires-Dist: azure-storage-file-datalake (>=12.2.3,<13.0.0); extra == "azure"
Requires-Dist: boto3 (>=1.17.5,<2.0.0); extra == "aws"
Requires-Dist: dock-r (>=0.2.0,<0.3.0)
Requires-Dist: docker (>=4.4.1,<5.0.0)
Requires-Dist: fire (>=0.4.0,<0.5.0)
Requires-Dist: importlib-metadata (>=3.4.0,<4.0.0)
Requires-Dist: logless (>=0.2.1,<0.3.0)
Requires-Dist: runnow (>=0.1.0.14,<0.2.0)
Requires-Dist: s3fs (<0.5.2); extra == "aws"
Requires-Dist: uio (>=0.2.0,<0.3.0)
